bigdl-core-npu/__init__.py
bigdl-core-npu/common.lib
bigdl-core-npu/ggml.dll
bigdl-core-npu/ggml.lib
bigdl-core-npu/llama-cli-npu.exe
bigdl-core-npu/llama.dll
bigdl-core-npu/llama.lib
bigdl-core-npu/llm-cli.exe
bigdl-core-npu/npu_llm.dll
bigdl-core-npu/npu_llm.lib
bigdl-core-npu/zlib1.dll
bigdl-core-npu/include/llamacpp/arg.h
bigdl-core-npu/include/llamacpp/common.h
bigdl-core-npu/include/llamacpp/ggml-alloc.h
bigdl-core-npu/include/llamacpp/ggml-backend.h
bigdl-core-npu/include/llamacpp/ggml.h
bigdl-core-npu/include/llamacpp/llama.h
bigdl-core-npu/include/llamacpp/log.h
bigdl-core-npu/include/npu/npu_common.h
bigdl-core-npu/include/npu/npu_llm.h
bigdl_core_npu-2.6.0.data/scripts/init-llama-cpp.bat
intel_npu_acceleration_library/__init__.py
intel_npu_acceleration_library/_version.py
intel_npu_acceleration_library/compiler.py
intel_npu_acceleration_library/device.py
intel_npu_acceleration_library/dtypes.py
intel_npu_acceleration_library/modelling.py
intel_npu_acceleration_library/optimizations.py
intel_npu_acceleration_library/quantization.py
intel_npu_acceleration_library/backend/__init__.py
intel_npu_acceleration_library/backend/base.py
intel_npu_acceleration_library/backend/bindings.py
intel_npu_acceleration_library/backend/compression.py
intel_npu_acceleration_library/backend/convolution.py
intel_npu_acceleration_library/backend/factory.py
intel_npu_acceleration_library/backend/linear.py
intel_npu_acceleration_library/backend/matmul.py
intel_npu_acceleration_library/backend/mlp.py
intel_npu_acceleration_library/backend/ops.py
intel_npu_acceleration_library/backend/qlinear.py
intel_npu_acceleration_library/backend/qmatmul.py
intel_npu_acceleration_library/backend/runtime.py
intel_npu_acceleration_library/backend/sdpa.py
intel_npu_acceleration_library/backend/tensor.py
intel_npu_acceleration_library/backend/utils.py
intel_npu_acceleration_library/bigdl-core-npu/cache.json
intel_npu_acceleration_library/bigdl-core-npu/openvino.dll
bigdl_core_npu-2.6.0.dist-info/METADATA
bigdl_core_npu-2.6.0.dist-info/WHEEL
bigdl_core_npu-2.6.0.dist-info/top_level.txt
bigdl_core_npu-2.6.0.dist-info/RECORD
